blockkit/__init__.py
blockkit/core.py
blockkit/py.typed
blockkit/utils.py
blockkit-2.1.3.dist-info/METADATA
blockkit-2.1.3.dist-info/WHEEL
blockkit-2.1.3.dist-info/licenses/LICENSE
blockkit-2.1.3.dist-info/RECORD
