Metadata-Version: 2.4
Name: blockkit
Version: 2.1.3
Summary: A fast way to build Block Kit interfaces in Python
Project-URL: Homepage, https://github.com/imryche/blockkit
Project-URL: Issues, https://github.com/imryche/blockkit/issues
Author-email: Dima Czernyszow <imryche13@gmail.com>
License-File: LICENSE
Classifier: License :: OSI Approved :: MIT License
Classifier: Operating System :: OS Independent
Classifier: Programming Language :: Python :: 3
Requires-Python: >=3.11
